{
  "description": {
    "all": [
      "sql",
      "http",
      "xml",
      "web",
      "security",
      "database",
      "json",
      "yaml",
      "validation",
      "sanitization",
      "cloud",
      "iam",
      "auth",
      "middleware",
      "serialization",
      "event",
      "stream",
      "rpc",
      "socket",
      "proto",
      "resource",
      "data",
      "sensitive",
      "template",
      "log",
      "logging",
      "service",
      "api",
      "slf4j",
      "parse",
      "emit",
      "jdbc",
      "connect",
      "pool",
      "beans",
      "transaction",
      "mysql",
      "postgres",
      "oracle",
      "mongo",
      "redis",
      "splunk",
      "stripe",
      "payment",
      "finance",
      "currency",
      "coin",
      "monero",
      "ssl",
      "traffic",
      "mvc",
      "html",
      "escape",
      "unescape",
      "rest",
      "tomcat",
      "hibernate",
      "orm",
      "aop",
      "jwt",
      "saml",
      "token",
      "tls",
      "codec",
      "cron",
      "crypto",
      "jce",
      "certificate",
      "developer",
      "tools",
      "autoconfigure",
      "test",
      "jsonpath",
      "bytecode",
      "mock",
      "injection",
      "comparators",
      "transform",
      "encode",
      "decode",
      "ldap",
      "owasp",
      "fileupload",
      "beanshell",
      "spel",
      "mail",
      "apacheds",
      "jndi",
      "ldif",
      "jdbm",
      "kerberos",
      "oidc",
      "oauth2",
      "cli",
      "binary",
      "ml",
      "ai",
      "azure",
      "gcp",
      "terraform",
      "redis",
      "valkey",
      "lint",
      "bundle",
      "object-persistence",
      "text-to-image",
      "translat",
      "object-detect",
      "mvc",
      "framework",
      "graph",
      "templates",
      "fastjson",
      "simd",
      "event-driven",
      "productivity",
      "typesafe",
      "projections",
      "performance",
      "plugins",
      "non-block",
      "microsoft"
    ]
  },
  "properties": {
    "all": [
      "sql",
      "http",
      "xml",
      "cloud",
      "middleware",
      "framework",
      "bluetooth",
      "wifi",
      "wireless",
      "driver",
      "graphics",
      "firmware",
      "gyroscope",
      "accelerometer",
      "mobile",
      "network",
      "battery",
      "matrix",
      "thunderbolt",
      "crypto",
      "algorithm",
      "encrypt",
      "decrypt",
      "registry",
      "maps",
      "payment",
      "stripe",
      "apple-pay",
      "icloud"
    ]
  },
  "name": {
    "obom": [
      { "devel": ["-(dev|devel|headers|sdk|libs)$", "^(git)-"] },
      { "bin": ["(-bin)$"] },
      { "kernel": ["^(linux|kernel)"] },
      {
        "security": [
          "(selinux|apparmor|security|openssl|libressl|gnutls|jose|keyutils|passwd)"
        ]
      },
      {
        "container": [
          "(container|podman|docker|runc|nerdctl|crun|libvirt|qemu)"
        ]
      },
      {
        "build": ["(cpp|fortran|gcc|make|meson|bazel|maven|gradle|sbt|ant|gdb)"]
      },
      {
        "network": [
          "(tailscale|wireguard|openvpn|dns|cockpit|cups|dhcp|network|iproute|iptables|mosh|netavark|openssh|rsync|tcpdump)"
        ]
      },
      { "webserver": ["(httpd|http2)"] },
      { "crypto": ["(crypt|gpg|keys|certificates|gnupg)"] },
      { "repository": ["(-repos|-release|ostree)"] },
      { "shell": ["(bash|zsh|csh|fish)"] },
      { "bluetooth": ["(bluez|bluetooth)"] },
      { "sound": ["(alsa|pulseaudio|wireplumber|flac|codecs|ldac|sound)"] },
      { "compression": ["(tar|zip|brotli|xz-utils|webp|zstd|lz4)"] },
      {
        "runtime": [
          "(perl|lua|php|python|ruby|dotnet|java|swift|runtime|glibc|musl|wasm)"
        ]
      },
      { "editor": ["(vim|emacs|nano|hexedit)"] },
      { "xml": ["(xml|expat)"] },
      { "boot": ["(grub|systemd-boot|syslinux)"] },
      { "gui": ["(wayland|xorg|X11|mesa|vulkan|tk|wkhtmltox)"] },
      { "package": ["(rpm|dnf|yum|apt|zypper|apk)"] }
    ]
  }
}
